shot_chart/__init__.py
shot_chart/_nbdev.py
shot_chart/core.py
shot_chart-1.1.1.dist-info/LICENSE
shot_chart-1.1.1.dist-info/METADATA
shot_chart-1.1.1.dist-info/WHEEL
shot_chart-1.1.1.dist-info/entry_points.txt
shot_chart-1.1.1.dist-info/top_level.txt
shot_chart-1.1.1.dist-info/RECORD
