Metadata-Version: 2.1
Name: shot-chart
Version: 1.1.1
Summary: plotting shot charts from basketball-reference.com
Home-page: https://github.com/theccalderon/shot_chart
Author: Cesar Calderon Muro
Author-email: cesar.calderon.dev@gmail.com
License: Apache Software License 2.0
Keywords: nba shot chart
Platform: UNKNOWN
Classifier: Development Status :: 3 - Alpha
Classifier: Intended Audience :: Developers
Classifier: License :: OSI Approved :: Apache Software License
Classifier: Natural Language :: English
Classifier: Programming Language :: Python :: 3.6
Classifier: Programming Language :: Python :: 3.7
Classifier: Programming Language :: Python :: 3.8
Requires-Python: >=3.6
Requires-Dist: asn1crypto (==1.3.0)
Requires-Dist: boto3 (==1.11.14)
Requires-Dist: fastprogress (==0.2.2)
Requires-Dist: matplotlib (==3.1.1)
Requires-Dist: pandas (==0.25.3)
Requires-Dist: requests (==2.22.0)
Requires-Dist: PyYAML (==5.3)
